manimbook_create/__init__.py
manimbook_create/convert.py
manimbook_create/templates/index.html
manimbook_create/templates/reveal.js/base.html.j2
manimbook_create/templates/reveal.js/conf.json
manimbook_create/templates/reveal.js/index.html.j2
manimbook_create/templates/reveal.js/static/custom_reveal.css
manimbook_create/templates/scroll.html
manimbook_create-0.1.4.dist-info/entry_points.txt
manimbook_create-0.1.4.dist-info/WHEEL
manimbook_create-0.1.4.dist-info/METADATA
manimbook_create-0.1.4.dist-info/RECORD
